deeptune/__init__.py
deeptune/client.py
deeptune/core/__init__.py
deeptune/core/api_error.py
deeptune/core/client_wrapper.py
deeptune/core/datetime_utils.py
deeptune/core/file.py
deeptune/core/http_client.py
deeptune/core/jsonable_encoder.py
deeptune/core/pydantic_utilities.py
deeptune/core/query_encoder.py
deeptune/core/remove_none_from_dict.py
deeptune/core/request_options.py
deeptune/environment.py
deeptune/py.typed
deeptune/text_to_speech/__init__.py
deeptune/text_to_speech/client.py
deeptune/types/__init__.py
deeptune/types/create_voice_response.py
deeptune/types/get_voice_by_id_response.py
deeptune/types/list_voices_response.py
deeptune/types/text_to_speech_from_prompt_response.py
deeptune/types/text_to_speech_response.py
deeptune/types/update_voice_response.py
deeptune/types/voice.py
deeptune/utils.py
deeptune/version.py
deeptune/voices/__init__.py
deeptune/voices/client.py
deeptune-1.0.3.dist-info/METADATA
deeptune-1.0.3.dist-info/WHEEL
deeptune-1.0.3.dist-info/RECORD
